README.rst
setup.py
aiowstunnel/__init__.py
aiowstunnel/client.py
aiowstunnel/connection.py
aiowstunnel/fwd_connection.py
aiowstunnel/ids.py
aiowstunnel/packets.py
aiowstunnel/resources
aiowstunnel/server.py
aiowstunnel/test_ids.py
aiowstunnel/test_packets.py
aiowstunnel/test_server.py
aiowstunnel.egg-info/PKG-INFO
aiowstunnel.egg-info/SOURCES.txt
aiowstunnel.egg-info/dependency_links.txt
aiowstunnel.egg-info/requires.txt
aiowstunnel.egg-info/top_level.txt
aiowstunnel/resources/asset-manifest.json
aiowstunnel/resources/favicon.ico
aiowstunnel/resources/index.html
aiowstunnel/resources/manifest.json
aiowstunnel/resources/service-worker.js
aiowstunnel/resources/static
aiowstunnel/resources/static/css
aiowstunnel/resources/static/js
aiowstunnel/resources/static/css/main.594fff57.css
aiowstunnel/resources/static/css/main.594fff57.css.map
aiowstunnel/resources/static/js/main.c198f799.js
aiowstunnel/resources/static/js/main.c198f799.js.map