Metadata-Version: 1.1
Name: aiowstunnel
Version: 0.4.3
Summary: Persistent and reliable TCP tunneling on websockets based on asyncio
Home-page: https://github.com/richardbann/aiowstunnel
Author: Richard Bann
Author-email: richardbann@gmail.com
License: MIT
Keywords: tunneling TCP websocket
Platform: UNKNOWN
Classifier: License :: OSI Approved :: MIT License
Classifier: Programming Language :: Python :: 3.6
